think_mcp_server/__init__.py
think_mcp_server/__main__.py
think_mcp_server/init.py
think_mcp_server/prompts.py
think_mcp_server/resources.py
think_mcp_server/server.py
think_mcp_server/templates.py
think_mcp_server/config/.env.template
think_mcp_server/config/servers_config.json
think_mcp_server/prompts/prompts-template.md
think_mcp_server/resources/resources-template.md
think_mcp_server/resources/tool_content_analyzer_prompt.md
think_mcp_server/tools/__init__.py
think_mcp_server/tools/article_analysis.py
think_mcp_server/tools/baidu_speech_recognizer.py
think_mcp_server/tools/content_analyzer.py
think_mcp_server/tools/speech_to_text.py
think_mcp_server/tools/video_audio_extractor.py
think_mcp_server-0.5.0.dist-info/METADATA
think_mcp_server-0.5.0.dist-info/WHEEL
think_mcp_server-0.5.0.dist-info/entry_points.txt
think_mcp_server-0.5.0.dist-info/licenses/LICENSE
think_mcp_server-0.5.0.dist-info/RECORD
