Metadata-Version: 2.4
Name: think-mcp-server
Version: 0.5.0
Summary: thinkthinking's mcp server
Project-URL: Homepage, https://github.com/thinkthinking/think-mcp-server
Project-URL: Bug Tracker, https://github.com/thinkthinking/think-mcp-server/issues
Project-URL: Documentation, https://github.com/thinkthinking/think-mcp-server#readme
Author-email: "zhenjie.ye" <yezhenjie@outlook.de>
License: MIT
License-File: LICENSE
Keywords: ai,mcp,server,think
Classifier: Development Status :: 4 - Beta
Classifier: Intended Audience :: Developers
Classifier: License :: OSI Approved :: MIT License
Classifier: Operating System :: OS Independent
Classifier: Programming Language :: Python :: 3
Classifier: Programming Language :: Python :: 3.12
Classifier: Topic :: Software Development :: Libraries :: Python Modules
Requires-Python: >=3.12
Requires-Dist: fastapi>=0.109.0
Requires-Dist: httpx[socks]>=0.28.1
Requires-Dist: mcp>=1.3.0
Requires-Dist: openai>=1.3.0
Requires-Dist: prompt-toolkit>=3.0.43
Requires-Dist: pyfiglet>=1.0.2
Requires-Dist: pytest-asyncio>=0.25.3
Requires-Dist: pytest-mock>=3.14.0
Requires-Dist: pytest>=8.3.4
Requires-Dist: python-dotenv>=1.0.0
Requires-Dist: pyyaml>=6.0.2
Requires-Dist: rich>=13.9.4
Requires-Dist: think-llm-client>=0.3.7
Requires-Dist: tiktoken>=0.8.0
Requires-Dist: time-machine>=2.13.0
Requires-Dist: urllib3>=2.0.0
Requires-Dist: uvicorn>=0.27.0
Requires-Dist: websockets>=12.0
Provides-Extra: dev
Requires-Dist: black>=24.3.0; extra == 'dev'
Requires-Dist: build>=1.2.0; extra == 'dev'
Requires-Dist: flake8>=7.0.0; extra == 'dev'
Requires-Dist: isort>=5.13.2; extra == 'dev'
Requires-Dist: mypy>=1.9.0; extra == 'dev'
Requires-Dist: pytest-asyncio>=0.25.3; extra == 'dev'
Requires-Dist: pytest-cov>=5.0.0; extra == 'dev'
Requires-Dist: pytest-mock>=3.14.0; extra == 'dev'
Requires-Dist: pytest>=8.3.4; extra == 'dev'
Requires-Dist: twine>=5.0.0; extra == 'dev'
